{"nodes": [{"id": "c_zigengine_zigengine_src_ecs_test_zig", "label": "ecs_test.zig", "file_type": "code", "source_file": "src/ecs_test.zig", "source_location": "L1"}], "edges": [{"source": "c_zigengine_zigengine_src_ecs_test_zig", "target": "std", "relation": "imports_from", "confidence": "EXTRACTED", "source_file": "src/ecs_test.zig", "source_location": "L1", "weight": 1.0}, {"source": "c_zigengine_zigengine_src_ecs_test_zig", "target": "registry", "relation": "imports_from", "confidence": "EXTRACTED", "source_file": "src/ecs_test.zig", "source_location": "L5", "weight": 1.0}, {"source": "c_zigengine_zigengine_src_ecs_test_zig", "target": "componentstorage", "relation": "imports_from", "confidence": "EXTRACTED", "source_file": "src/ecs_test.zig", "source_location": "L6", "weight": 1.0}, {"source": "c_zigengine_zigengine_src_ecs_test_zig", "target": "event", "relation": "imports_from", "confidence": "EXTRACTED", "source_file": "src/ecs_test.zig", "source_location": "L7", "weight": 1.0}, {"source": "c_zigengine_zigengine_src_ecs_test_zig", "target": "system", "relation": "imports_from", "confidence": "EXTRACTED", "source_file": "src/ecs_test.zig", "source_location": "L9", "weight": 1.0}, {"source": "c_zigengine_zigengine_src_ecs_test_zig", "target": "camera_system", "relation": "imports_from", "confidence": "EXTRACTED", "source_file": "src/ecs_test.zig", "source_location": "L10", "weight": 1.0}, {"source": "c_zigengine_zigengine_src_ecs_test_zig", "target": "movement_system", "relation": "imports_from", "confidence": "EXTRACTED", "source_file": "src/ecs_test.zig", "source_location": "L11", "weight": 1.0}, {"source": "c_zigengine_zigengine_src_ecs_test_zig", "target": "input_system", "relation": "imports_from", "confidence": "EXTRACTED", "source_file": "src/ecs_test.zig", "source_location": "L12", "weight": 1.0}, {"source": "c_zigengine_zigengine_src_ecs_test_zig", "target": "math", "relation": "imports_from", "confidence": "EXTRACTED", "source_file": "src/ecs_test.zig", "source_location": "L14", "weight": 1.0}, {"source": "c_zigengine_zigengine_src_ecs_test_zig", "target": "meshcache", "relation": "imports_from", "confidence": "EXTRACTED", "source_file": "src/ecs_test.zig", "source_location": "L16", "weight": 1.0}], "raw_calls": []}