{"nodes": [{"id": "c_zigengine_zigengine_src_renderer_zvulkancontext_zig", "label": "zVulkanContext.zig", "file_type": "code", "source_file": "src/renderer/zVulkanContext.zig", "source_location": "L1"}, {"id": "renderer_zvulkancontext_shaderdata", "label": "ShaderData", "file_type": "code", "source_file": "src/renderer/zVulkanContext.zig", "source_location": "L16"}, {"id": "renderer_zvulkancontext_shaderdatabuffer", "label": "ShaderDataBuffer", "file_type": "code", "source_file": "src/renderer/zVulkanContext.zig", "source_location": "L21"}, {"id": "renderer_zvulkancontext_vertex", "label": "Vertex", "file_type": "code", "source_file": "src/renderer/zVulkanContext.zig", "source_location": "L27"}, {"id": "renderer_zvulkancontext_pushconstants", "label": "PushConstants", "file_type": "code", "source_file": "src/renderer/zVulkanContext.zig", "source_location": "L32"}, {"id": "renderer_zvulkancontext_frameubo", "label": "FrameUBO", "file_type": "code", "source_file": "src/renderer/zVulkanContext.zig", "source_location": "L37"}, {"id": "renderer_zvulkancontext_textureslot", "label": "TextureSlot", "file_type": "code", "source_file": "src/renderer/zVulkanContext.zig", "source_location": "L41"}, {"id": "renderer_zvulkancontext_vulkancontext", "label": "VulkanContext", "file_type": "code", "source_file": "src/renderer/zVulkanContext.zig", "source_location": "L47"}], "edges": [{"source": "c_zigengine_zigengine_src_renderer_zvulkancontext_zig", "target": "std", "relation": "imports_from", "confidence": "EXTRACTED", "source_file": "src/renderer/zVulkanContext.zig", "source_location": "L1", "weight": 1.0}, {"source": "c_zigengine_zigengine_src_renderer_zvulkancontext_zig", "target": "builtin", "relation": "imports_from", "confidence": "EXTRACTED", "source_file": "src/renderer/zVulkanContext.zig", "source_location": "L2", "weight": 1.0}, {"source": "c_zigengine_zigengine_src_renderer_zvulkancontext_zig", "target": "vmaimport", "relation": "imports_from", "confidence": "EXTRACTED", "source_file": "src/renderer/zVulkanContext.zig", "source_location": "L3", "weight": 1.0}, {"source": "c_zigengine_zigengine_src_renderer_zvulkancontext_zig", "target": "zvkgl", "relation": "imports_from", "confidence": "EXTRACTED", "source_file": "src/renderer/zVulkanContext.zig", "source_location": "L4", "weight": 1.0}, {"source": "c_zigengine_zigengine_src_renderer_zvulkancontext_zig", "target": "window", "relation": "imports_from", "confidence": "EXTRACTED", "source_file": "src/renderer/zVulkanContext.zig", "source_location": "L5", "weight": 1.0}, {"source": "c_zigengine_zigengine_src_renderer_zvulkancontext_zig", "target": "renderer_zvulkancontext_shaderdata", "relation": "contains", "confidence": "EXTRACTED", "source_file": "src/renderer/zVulkanContext.zig", "source_location": "L16", "weight": 1.0}, {"source": "c_zigengine_zigengine_src_renderer_zvulkancontext_zig", "target": "renderer_zvulkancontext_shaderdatabuffer", "relation": "contains", "confidence": "EXTRACTED", "source_file": "src/renderer/zVulkanContext.zig", "source_location": "L21", "weight": 1.0}, {"source": "c_zigengine_zigengine_src_renderer_zvulkancontext_zig", "target": "renderer_zvulkancontext_vertex", "relation": "contains", "confidence": "EXTRACTED", "source_file": "src/renderer/zVulkanContext.zig", "source_location": "L27", "weight": 1.0}, {"source": "c_zigengine_zigengine_src_renderer_zvulkancontext_zig", "target": "renderer_zvulkancontext_pushconstants", "relation": "contains", "confidence": "EXTRACTED", "source_file": "src/renderer/zVulkanContext.zig", "source_location": "L32", "weight": 1.0}, {"source": "c_zigengine_zigengine_src_renderer_zvulkancontext_zig", "target": "renderer_zvulkancontext_frameubo", "relation": "contains", "confidence": "EXTRACTED", "source_file": "src/renderer/zVulkanContext.zig", "source_location": "L37", "weight": 1.0}, {"source": "c_zigengine_zigengine_src_renderer_zvulkancontext_zig", "target": "renderer_zvulkancontext_textureslot", "relation": "contains", "confidence": "EXTRACTED", "source_file": "src/renderer/zVulkanContext.zig", "source_location": "L41", "weight": 1.0}, {"source": "c_zigengine_zigengine_src_renderer_zvulkancontext_zig", "target": "renderer_zvulkancontext_vulkancontext", "relation": "contains", "confidence": "EXTRACTED", "source_file": "src/renderer/zVulkanContext.zig", "source_location": "L47", "weight": 1.0}], "raw_calls": []}