{"nodes": [{"id": "c_zigengine_zigengine_src_engine_ecs_systems_system_zig", "label": "system.zig", "file_type": "code", "source_file": "src/engine/ecs/systems/system.zig", "source_location": "L1"}, {"id": "systems_system_system", "label": "System", "file_type": "code", "source_file": "src/engine/ecs/systems/system.zig", "source_location": "L4"}, {"id": "systems_system_systemrunner", "label": "SystemRunner", "file_type": "code", "source_file": "src/engine/ecs/systems/system.zig", "source_location": "L13"}, {"id": "systems_system_systemrunner_init", "label": ".init()", "file_type": "code", "source_file": "src/engine/ecs/systems/system.zig", "source_location": "L17"}, {"id": "systems_system_systemrunner_deinit", "label": ".deinit()", "file_type": "code", "source_file": "src/engine/ecs/systems/system.zig", "source_location": "L21"}, {"id": "systems_system_systemrunner_addsystem", "label": ".addSystem()", "file_type": "code", "source_file": "src/engine/ecs/systems/system.zig", "source_location": "L25"}, {"id": "systems_system_systemrunner_initall", "label": ".initAll()", "file_type": "code", "source_file": "src/engine/ecs/systems/system.zig", "source_location": "L34"}, {"id": "systems_system_systemrunner_deinitall", "label": ".deinitAll()", "file_type": "code", "source_file": "src/engine/ecs/systems/system.zig", "source_location": "L40"}, {"id": "systems_system_systemrunner_update", "label": ".update()", "file_type": "code", "source_file": "src/engine/ecs/systems/system.zig", "source_location": "L46"}, {"id": "systems_system_noopupdate", "label": "noopUpdate()", "file_type": "code", "source_file": "src/engine/ecs/systems/system.zig", "source_location": "L53"}, {"id": "systems_system_noopinit", "label": "noopInit()", "file_type": "code", "source_file": "src/engine/ecs/systems/system.zig", "source_location": "L54"}, {"id": "systems_system_noopdeinit", "label": "noopDeinit()", "file_type": "code", "source_file": "src/engine/ecs/systems/system.zig", "source_location": "L55"}, {"id": "systems_system_ordertracker", "label": "OrderTracker", "file_type": "code", "source_file": "src/engine/ecs/systems/system.zig", "source_location": "L57"}, {"id": "systems_system_ordertracker_update", "label": ".update()", "file_type": "code", "source_file": "src/engine/ecs/systems/system.zig", "source_location": "L60"}, {"id": "systems_system_inittracker", "label": "InitTracker", "file_type": "code", "source_file": "src/engine/ecs/systems/system.zig", "source_location": "L110"}, {"id": "systems_system_inittracker_init", "label": ".init()", "file_type": "code", "source_file": "src/engine/ecs/systems/system.zig", "source_location": "L112"}, {"id": "systems_system_deinittracker", "label": "DeinitTracker", "file_type": "code", "source_file": "src/engine/ecs/systems/system.zig", "source_location": "L136"}, {"id": "systems_system_deinittracker_deinit", "label": ".deinit()", "file_type": "code", "source_file": "src/engine/ecs/systems/system.zig", "source_location": "L138"}], "edges": [{"source": "c_zigengine_zigengine_src_engine_ecs_systems_system_zig", "target": "std", "relation": "imports_from", "confidence": "EXTRACTED", "source_file": "src/engine/ecs/systems/system.zig", "source_location": "L1", "weight": 1.0}, {"source": "c_zigengine_zigengine_src_engine_ecs_systems_system_zig", "target": "registry", "relation": "imports_from", "confidence": "EXTRACTED", "source_file": "src/engine/ecs/systems/system.zig", "source_location": "L2", "weight": 1.0}, {"source": "c_zigengine_zigengine_src_engine_ecs_systems_system_zig", "target": "systems_system_system", "relation": "contains", "confidence": "EXTRACTED", "source_file": "src/engine/ecs/systems/system.zig", "source_location": "L4", "weight": 1.0}, {"source": "c_zigengine_zigengine_src_engine_ecs_systems_system_zig", "target": "systems_system_systemrunner", "relation": "contains", "confidence": "EXTRACTED", "source_file": "src/engine/ecs/systems/system.zig", "source_location": "L13", "weight": 1.0}, {"source": "systems_system_systemrunner", "target": "systems_system_systemrunner_init", "relation": "method", "confidence": "EXTRACTED", "source_file": "src/engine/ecs/systems/system.zig", "source_location": "L17", "weight": 1.0}, {"source": "systems_system_systemrunner", "target": "systems_system_systemrunner_deinit", "relation": "method", "confidence": "EXTRACTED", "source_file": "src/engine/ecs/systems/system.zig", "source_location": "L21", "weight": 1.0}, {"source": "systems_system_systemrunner", "target": "systems_system_systemrunner_addsystem", "relation": "method", "confidence": "EXTRACTED", "source_file": "src/engine/ecs/systems/system.zig", "source_location": "L25", "weight": 1.0}, {"source": "systems_system_systemrunner", "target": "systems_system_systemrunner_initall", "relation": "method", "confidence": "EXTRACTED", "source_file": "src/engine/ecs/systems/system.zig", "source_location": "L34", "weight": 1.0}, {"source": "systems_system_systemrunner", "target": "systems_system_systemrunner_deinitall", "relation": "method", "confidence": "EXTRACTED", "source_file": "src/engine/ecs/systems/system.zig", "source_location": "L40", "weight": 1.0}, {"source": "systems_system_systemrunner", "target": "systems_system_systemrunner_update", "relation": "method", "confidence": "EXTRACTED", "source_file": "src/engine/ecs/systems/system.zig", "source_location": "L46", "weight": 1.0}, {"source": "c_zigengine_zigengine_src_engine_ecs_systems_system_zig", "target": "systems_system_noopupdate", "relation": "contains", "confidence": "EXTRACTED", "source_file": "src/engine/ecs/systems/system.zig", "source_location": "L53", "weight": 1.0}, {"source": "c_zigengine_zigengine_src_engine_ecs_systems_system_zig", "target": "systems_system_noopinit", "relation": "contains", "confidence": "EXTRACTED", "source_file": "src/engine/ecs/systems/system.zig", "source_location": "L54", "weight": 1.0}, {"source": "c_zigengine_zigengine_src_engine_ecs_systems_system_zig", "target": "systems_system_noopdeinit", "relation": "contains", "confidence": "EXTRACTED", "source_file": "src/engine/ecs/systems/system.zig", "source_location": "L55", "weight": 1.0}, {"source": "c_zigengine_zigengine_src_engine_ecs_systems_system_zig", "target": "systems_system_ordertracker", "relation": "contains", "confidence": "EXTRACTED", "source_file": "src/engine/ecs/systems/system.zig", "source_location": "L57", "weight": 1.0}, {"source": "systems_system_ordertracker", "target": "systems_system_ordertracker_update", "relation": "method", "confidence": "EXTRACTED", "source_file": "src/engine/ecs/systems/system.zig", "source_location": "L60", "weight": 1.0}, {"source": "c_zigengine_zigengine_src_engine_ecs_systems_system_zig", "target": "systems_system_inittracker", "relation": "contains", "confidence": "EXTRACTED", "source_file": "src/engine/ecs/systems/system.zig", "source_location": "L110", "weight": 1.0}, {"source": "systems_system_inittracker", "target": "systems_system_inittracker_init", "relation": "method", "confidence": "EXTRACTED", "source_file": "src/engine/ecs/systems/system.zig", "source_location": "L112", "weight": 1.0}, {"source": "c_zigengine_zigengine_src_engine_ecs_systems_system_zig", "target": "systems_system_deinittracker", "relation": "contains", "confidence": "EXTRACTED", "source_file": "src/engine/ecs/systems/system.zig", "source_location": "L136", "weight": 1.0}, {"source": "systems_system_deinittracker", "target": "systems_system_deinittracker_deinit", "relation": "method", "confidence": "EXTRACTED", "source_file": "src/engine/ecs/systems/system.zig", "source_location": "L138", "weight": 1.0}], "raw_calls": [{"caller_nid": "systems_system_systemrunner_deinit", "callee": "deinit", "is_member_call": true, "source_file": "C:\\zigEngine\\ZigEngine\\src\\engine\\ecs\\systems\\system.zig", "source_location": "L22"}, {"caller_nid": "systems_system_systemrunner_addsystem", "callee": "append", "is_member_call": true, "source_file": "C:\\zigEngine\\ZigEngine\\src\\engine\\ecs\\systems\\system.zig", "source_location": "L26"}, {"caller_nid": "systems_system_systemrunner_addsystem", "callee": "sort", "is_member_call": true, "source_file": "C:\\zigEngine\\ZigEngine\\src\\engine\\ecs\\systems\\system.zig", "source_location": "L27"}, {"caller_nid": "systems_system_systemrunner_initall", "callee": "f", "is_member_call": false, "source_file": "C:\\zigEngine\\ZigEngine\\src\\engine\\ecs\\systems\\system.zig", "source_location": "L36"}, {"caller_nid": "systems_system_systemrunner_deinitall", "callee": "f", "is_member_call": false, "source_file": "C:\\zigEngine\\ZigEngine\\src\\engine\\ecs\\systems\\system.zig", "source_location": "L42"}, {"caller_nid": "systems_system_systemrunner_update", "callee": "update_fn", "is_member_call": true, "source_file": "C:\\zigEngine\\ZigEngine\\src\\engine\\ecs\\systems\\system.zig", "source_location": "L48"}, {"caller_nid": "systems_system_ordertracker_update", "callee": "append", "is_member_call": true, "source_file": "C:\\zigEngine\\ZigEngine\\src\\engine\\ecs\\systems\\system.zig", "source_location": "L62"}]}